netstoragekit/__init__.py
netstoragekit/api.py
netstoragekit/auth.py
netstoragekit/exceptions.py
netstoragekit/utils.py
NetStorageKit-1.0.8.dist-info/DESCRIPTION.rst
NetStorageKit-1.0.8.dist-info/METADATA
NetStorageKit-1.0.8.dist-info/metadata.json
NetStorageKit-1.0.8.dist-info/RECORD
NetStorageKit-1.0.8.dist-info/top_level.txt
NetStorageKit-1.0.8.dist-info/WHEEL
Users/ernesto/netstoragekit_test_credentials.json.dist
