Metadata-Version: 2.0
Name: NetStorageKit
Version: 1.0.8
Summary: Akamai's NetStorage API communication kit
Home-page: https://github.com/MentaNetwork/NetStorageKit-Python
Author: Ernesto Mendoza Blanco
Author-email: ernestom@mentanetwork.com
License: MIT License
Download-URL: https://github.com/MentaNetwork/NetStorageKit-Python
Platform: UNKNOWN
Classifier: Development Status :: 5 - Production/Stable
Classifier: Environment :: Console
Classifier: Intended Audience :: Developers
Classifier: Intended Audience :: System Administrators
Classifier: License :: OSI Approved :: MIT License
Classifier: Operating System :: MacOS :: MacOS X
Classifier: Operating System :: Microsoft :: Windows
Classifier: Operating System :: POSIX
Classifier: Programming Language :: Python
Requires-Dist: requests
Requires-Dist: responses
Requires-Dist: pytest
Requires-Dist: ntplib
Requires-Dist: pytest-cov
Requires-Dist: requests[security]
